pyagentlayer/__init__.py
pyagentlayer/agent.py
pyagentlayer/agent_executor.py
pyagentlayer/agent_link.py
pyagentlayer/agent_logger.py
pyagentlayer/models.py
pyagentlayer/registry_client.py
pyagentlayer/abi/AGENT.json
pyagentlayer/abi/AgentNFT.json
pyagentlayer/abi/SmartWallet.json
pyagentlayer/abi/SmartWalletFactory.json
pyagentlayer/abi/Subscription.json
pyagentlayer/abi/SubscriptionUsage.json
pyagentlayer/utils/__init__.py
pyagentlayer/utils/base_request.py
pyagentlayer/utils/command.py
pyagentlayer/utils/exceptions.py
pyagentlayer/utils/ipfs.py
PyAgentlayer-0.1.0.dist-info/LICENSE
PyAgentlayer-0.1.0.dist-info/METADATA
PyAgentlayer-0.1.0.dist-info/WHEEL
PyAgentlayer-0.1.0.dist-info/top_level.txt
PyAgentlayer-0.1.0.dist-info/RECORD
