Metadata-Version: 2.1
Name: PyAgentlayer
Version: 0.1.0
Summary: python sdk for agentlayer
Home-page: https://github.com/MetaTrustLabs/AgentLayerSDK
Author: Metatrust Labs
License: AGPL-3.0
Requires-Python: >=3.10
License-File: LICENSE
Requires-Dist: web3 >=6.0.0
Requires-Dist: Flask >=3.0.2
Requires-Dist: requests >=2.31.0
Requires-Dist: python-dotenv >=1.0.1
Requires-Dist: pydantic >=2.6.4
